{
  "mudlet": {
    "version": "unknown"
  },
  "rooms": [
    {
      "name": "The Gate to the Wilderness",
      "exits": {
        "west": 116
      },
      "id": 115
    },
    {
      "name": "Intersection of Park Street and Caravan Road",
      "exits": {
        "south": 233,
        "west": 117,
        "east": 115,
        "north": 172
      },
      "id": 116
    },
    {
      "name": "Intersection of Park Street and Via Sacra",
      "exits": {
        "south": 220,
        "west": 118,
        "east": 116,
        "north": 226
      },
      "id": 117
    },
    {
      "name": "A shaded walk",
      "exits": {
        "south": 221,
        "west": 119,
        "east": 117,
        "north": 227
      },
      "id": 118
    },
    {
      "name": "A shaded walk",
      "exits": {
        "south": 222,
        "west": 120,
        "east": 118,
        "north": 230
      },
      "id": 119
    },
    {
      "name": "A shaded walk",
      "exits": {
        "west": 121,
        "east": 119,
        "south": 223
      },
      "id": 120
    },
    {
      "name": "A shaded walk",
      "exits": {
        "south": 224,
        "west": 122,
        "east": 120,
        "north": 425
      },
      "id": 121
    },
    {
      "name": "A shaded walk",
      "exits": {
        "south": 225,
        "west": 123,
        "east": 121,
        "north": 410
      },
      "id": 122
    },
    {
      "name": "A shaded walk",
      "exits": {
        "west": 124,
        "east": 122,
        "north": 411
      },
      "id": 123
    },
    {
      "name": "A break in the coverage",
      "exits": {
        "west": 125,
        "east": 123,
        "north": 412
      },
      "id": 124
    },
    {
      "name": "A busy intersection",
      "exits": {
        "south": 159,
        "west": 126,
        "east": 124,
        "north": 160
      },
      "id": 125
    },
    {
      "name": "The end of the park street",
      "exits": {
        "south": 880,
        "west": 127,
        "east": 125,
        "north": 879
      },
      "id": 126
    },
    {
      "name": "Entrance to the Old City.",
      "exits": {
        "west": 128,
        "east": 126,
        "north": 878
      },
      "id": 127
    },
    {
      "name": "Westroad, The Entrance to the Old City.",
      "exits": {
        "west": 129,
        "east": 127,
        "north": 881
      },
      "id": 128
    },
    {
      "name": "Westroad",
      "exits": {
        "west": 130,
        "east": 128,
        "south": 419
      },
      "id": 129
    },
    {
      "name": "Westroad",
      "exits": {
        "west": 131,
        "east": 129,
        "south": 420
      },
      "id": 130
    },
    {
      "name": "Westroad",
      "exits": {
        "west": 132,
        "east": 130,
        "north": 858
      },
      "id": 131
    },
    {
      "name": "Westroad",
      "exits": {
        "west": 133,
        "east": 131,
        "south": 421
      },
      "id": 132
    },
    {
      "name": "The corner of Westroad and Basalt Avenue",
      "exits": {
        "west": 134,
        "east": 132,
        "south": 135
      },
      "id": 133
    },
    {
      "name": "Western Gate of Vesla",
      "exits": {
        "east": 133
      },
      "id": 134
    },
    {
      "name": "Basalt Avenue",
      "exits": {
        "south": 136,
        "north": 133
      },
      "id": 135
    },
    {
      "name": "Basalt Avenue",
      "exits": {
        "south": 137,
        "north": 135
      },
      "id": 136
    },
    {
      "name": "Intersection of Basalt Avenue and Rapier Way",
      "exits": {
        "south": 138,
        "east": 193,
        "north": 136
      },
      "id": 137
    },
    {
      "name": "Basalt Avenue",
      "exits": {
        "south": 139,
        "west": 856,
        "east": 855,
        "north": 137
      },
      "id": 138
    },
    {
      "name": "Basalt Avenue",
      "exits": {
        "south": 140,
        "west": 853,
        "east": 854,
        "north": 138
      },
      "id": 139
    },
    {
      "name": "Intersection of Basalt Avenue and Street of the Bells",
      "exits": {
        "south": 141,
        "east": 204,
        "north": 139
      },
      "id": 140
    },
    {
      "name": "Basalt Avenue",
      "exits": {
        "south": 142,
        "north": 140
      },
      "id": 141
    },
    {
      "name": "Basalt Avenue",
      "exits": {
        "south": 143,
        "east": 850,
        "north": 141
      },
      "id": 142
    },
    {
      "name": "Corner of Basalt Avenue and West River Street",
      "exits": {
        "east": 144,
        "north": 142
      },
      "id": 143
    },
    {
      "name": "West River Street",
      "exits": {
        "west": 143,
        "east": 145,
        "south": 847
      },
      "id": 144
    },
    {
      "name": "West River Street",
      "exits": {
        "east": 146,
        "west": 144
      },
      "id": 145
    },
    {
      "name": "West River Street",
      "exits": {
        "south": 845,
        "west": 145,
        "east": 147,
        "north": 842
      },
      "id": 146
    },
    {
      "name": "West River Street",
      "exits": {
        "south": 846,
        "west": 146,
        "east": 148,
        "north": 841
      },
      "id": 147
    },
    {
      "name": "West River Street",
      "exits": {
        "west": 147,
        "east": 149,
        "north": 840
      },
      "id": 148
    },
    {
      "name": "West River street",
      "exits": {
        "east": 150,
        "west": 148
      },
      "id": 149
    },
    {
      "name": "West River street",
      "exits": {
        "east": 151,
        "west": 149
      },
      "id": 150
    },
    {
      "name": "River Street and South Main",
      "exits": {
        "south": 816,
        "west": 150,
        "east": 205,
        "north": 152
      },
      "id": 151
    },
    {
      "name": "South Main street",
      "exits": {
        "south": 151,
        "west": 819,
        "east": 817,
        "north": 153
      },
      "id": 152
    },
    {
      "name": "South Main Street",
      "exits": {
        "west": 820,
        "south": 152,
        "north": 154
      },
      "id": 153
    },
    {
      "name": "South Main Street",
      "exits": {
        "south": 153,
        "east": 821,
        "north": 155
      },
      "id": 154
    },
    {
      "name": "South Main Street",
      "exits": {
        "south": 154,
        "west": 423,
        "east": 422,
        "north": 156
      },
      "id": 155
    },
    {
      "name": "South Main Street",
      "exits": {
        "south": 155,
        "west": 822,
        "east": 424,
        "north": 157
      },
      "id": 156
    },
    {
      "name": "South Main Street",
      "exits": {
        "south": 156,
        "west": 823,
        "east": 830,
        "north": 158
      },
      "id": 157
    },
    {
      "name": "South Main street",
      "exits": {
        "west": 824,
        "south": 157,
        "north": 159
      },
      "id": 158
    },
    {
      "name": "South Main street",
      "exits": {
        "south": 158,
        "north": 125
      },
      "id": 159
    },
    {
      "name": "Northern Main",
      "exits": {
        "south": 125,
        "east": 412,
        "north": 161
      },
      "id": 160
    },
    {
      "name": "Northern Main Street",
      "exits": {
        "south": 160,
        "east": 808,
        "north": 162
      },
      "id": 161
    },
    {
      "name": "Northern Main street",
      "exits": {
        "south": 161,
        "east": 810,
        "north": 163
      },
      "id": 162
    },
    {
      "name": "Northern Main Street",
      "exits": {
        "south": 162,
        "east": 811,
        "north": 164
      },
      "id": 163
    },
    {
      "name": "Northern Main street",
      "exits": {
        "south": 163,
        "east": 812,
        "north": 165
      },
      "id": 164
    },
    {
      "name": "Northern Main street",
      "exits": {
        "south": 164,
        "north": 166
      },
      "id": 165
    },
    {
      "name": "Intersection of North Main and Scholar's Way",
      "exits": {
        "south": 165,
        "east": 192,
        "north": 167
      },
      "id": 166
    },
    {
      "name": "Northern Main street",
      "exits": {
        "south": 166,
        "north": 168
      },
      "id": 167
    },
    {
      "name": "Intersection of North Main and Wall Street",
      "exits": {
        "south": 167,
        "west": 793,
        "east": 170,
        "north": 169
      },
      "id": 168
    },
    {
      "name": "Northern Gate",
      "exits": {
        "south": 168,
        "northeast": 753
      },
      "id": 169
    },
    {
      "name": "Western End of Wall Street",
      "exits": {
        "east": 171,
        "west": 168
      },
      "id": 170
    },
    {
      "name": "Wall Street",
      "exits": {
        "west": 170
      },
      "id": 171
    },
    {
      "name": "Caravan Road",
      "exits": {
        "south": 116,
        "west": 226,
        "east": 735,
        "north": 173
      },
      "id": 172
    },
    {
      "name": "Caravan Road",
      "exits": {
        "south": 172,
        "west": 232,
        "east": 736,
        "north": 174
      },
      "id": 173
    },
    {
      "name": "Caravan Road",
      "exits": {
        "south": 173,
        "north": 175
      },
      "id": 174
    },
    {
      "name": "Caravan Road",
      "exits": {
        "south": 174,
        "north": 176
      },
      "id": 175
    },
    {
      "name": "Caravan Road",
      "exits": {
        "south": 175,
        "north": 177
      },
      "id": 176
    },
    {
      "name": "Caravan Road",
      "exits": {
        "south": 176,
        "north": 178
      },
      "id": 177
    },
    {
      "name": "Intersection of Scholar's Way and Caravan Road",
      "exits": {
        "west": 185,
        "south": 177,
        "north": 179
      },
      "id": 178
    },
    {
      "name": "Caravan Road",
      "exits": {
        "south": 178,
        "north": 180
      },
      "id": 179
    },
    {
      "name": "Intersection of Caravan Road and Wall Street",
      "exits": {
        "west": 181,
        "south": 179
      },
      "id": 180
    },
    {
      "name": "Eastern End of Wall Street",
      "exits": {
        "east": 180,
        "west": 182
      },
      "id": 181
    },
    {
      "name": "Wall Street",
      "exits": {
        "east": 181,
        "west": 183
      },
      "id": 182
    },
    {
      "name": "Wall Street",
      "exits": {
        "east": 182,
        "west": 184
      },
      "id": 183
    },
    {
      "name": "Wall Street",
      "exits": {
        "east": 183
      },
      "id": 184
    },
    {
      "name": "Scholar's Way",
      "exits": {
        "east": 178,
        "west": 186
      },
      "id": 185
    },
    {
      "name": "Scholar's Way",
      "exits": {
        "east": 185,
        "west": 187
      },
      "id": 186
    },
    {
      "name": "Scholar's Way",
      "exits": {
        "west": 188,
        "east": 186,
        "north": 737
      },
      "id": 187
    },
    {
      "name": "Scholar's Way",
      "exits": {
        "west": 189,
        "east": 187,
        "north": 738
      },
      "id": 188
    },
    {
      "name": "Scholar's Way",
      "exits": {
        "west": 190,
        "east": 188,
        "south": 739
      },
      "id": 189
    },
    {
      "name": "Scholar's Way",
      "exits": {
        "south": 740,
        "west": 191,
        "east": 189,
        "north": 741
      },
      "id": 190
    },
    {
      "name": "Scholar's Way",
      "exits": {
        "south": 742,
        "west": 192,
        "east": 190,
        "north": 743
      },
      "id": 191
    },
    {
      "name": "Scholar's Way",
      "exits": {
        "west": 166,
        "east": 191,
        "south": 744
      },
      "id": 192
    },
    {
      "name": "Rapier Way",
      "exits": {
        "east": 194,
        "west": 137
      },
      "id": 193
    },
    {
      "name": "Rapier Way",
      "exits": {
        "east": 195,
        "west": 193
      },
      "id": 194
    },
    {
      "name": "Rapier Way",
      "exits": {
        "east": 196,
        "west": 194
      },
      "id": 195
    },
    {
      "name": "Rapier Way",
      "exits": {
        "east": 197,
        "west": 195
      },
      "id": 196
    },
    {
      "name": "Intersection of Rapier Way and Zand Boulevard",
      "exits": {
        "west": 196,
        "south": 198
      },
      "id": 197
    },
    {
      "name": "Zand Boulevard",
      "exits": {
        "south": 199,
        "east": 857,
        "north": 197
      },
      "id": 198
    },
    {
      "name": "Zand Boulevard",
      "exits": {
        "south": 200,
        "east": 962,
        "north": 198
      },
      "id": 199
    },
    {
      "name": "Intersection of Street of the Bells and Zand Boulevard",
      "exits": {
        "west": 201,
        "north": 199
      },
      "id": 200
    },
    {
      "name": "Street of the Bells",
      "exits": {
        "south": 843,
        "west": 202,
        "east": 200,
        "north": 931
      },
      "id": 201
    },
    {
      "name": "Street of the Bells",
      "exits": {
        "west": 203,
        "east": 201,
        "south": 844
      },
      "id": 202
    },
    {
      "name": "Street of the Bells",
      "exits": {
        "east": 202,
        "west": 204
      },
      "id": 203
    },
    {
      "name": "Street of the Bells",
      "exits": {
        "east": 203,
        "west": 140
      },
      "id": 204
    },
    {
      "name": "East River Street",
      "exits": {
        "east": 206,
        "west": 151
      },
      "id": 205
    },
    {
      "name": "East River Street",
      "exits": {
        "west": 205,
        "east": 207,
        "north": 397
      },
      "id": 206
    },
    {
      "name": "East River Street",
      "exits": {
        "east": 208,
        "west": 206
      },
      "id": 207
    },
    {
      "name": "East River Street",
      "exits": {
        "west": 207,
        "east": 209,
        "north": 396
      },
      "id": 208
    },
    {
      "name": "East River Street",
      "exits": {
        "west": 208,
        "east": 210,
        "north": 395
      },
      "id": 209
    },
    {
      "name": "East River Street",
      "exits": {
        "west": 209,
        "east": 211,
        "north": 394
      },
      "id": 210
    },
    {
      "name": "End of East River Street",
      "exits": {
        "east": 212,
        "west": 210
      },
      "id": 211
    },
    {
      "name": "Intersection of Via Sacra and River Street",
      "exits": {
        "west": 211,
        "north": 213
      },
      "id": 212
    },
    {
      "name": "South End of Via Sacra",
      "exits": {
        "south": 212,
        "east": 399,
        "north": 214
      },
      "id": 213
    },
    {
      "name": "Southern Via Sacra",
      "exits": {
        "south": 213,
        "west": 400,
        "east": 401,
        "north": 215
      },
      "id": 214
    },
    {
      "name": "Via Sacra",
      "exits": {
        "south": 214,
        "north": 216
      },
      "id": 215
    },
    {
      "name": "Via Sacra",
      "exits": {
        "south": 215,
        "west": 402,
        "east": 403,
        "north": 217
      },
      "id": 216
    },
    {
      "name": "Via Sacra",
      "exits": {
        "west": 408,
        "south": 216,
        "north": 218
      },
      "id": 217
    },
    {
      "name": "Via Sacra",
      "exits": {
        "south": 217,
        "north": 219
      },
      "id": 218
    },
    {
      "name": "Via Sacra",
      "exits": {
        "west": 409,
        "south": 218,
        "north": 220
      },
      "id": 219
    },
    {
      "name": "Northern End of Via Sacra",
      "exits": {
        "south": 219,
        "west": 221,
        "east": 233,
        "north": 117
      },
      "id": 220
    },
    {
      "name": "General Store",
      "exits": {
        "west": 222,
        "east": 220,
        "north": 118
      },
      "id": 221
    },
    {
      "name": "Comfortably Numb",
      "exits": {
        "west": 223,
        "east": 221,
        "north": 119
      },
      "id": 222
    },
    {
      "name": "Medieval Mounts",
      "exits": {
        "west": 224,
        "east": 222,
        "north": 120
      },
      "id": 223
    },
    {
      "name": "Big Hole Banking",
      "exits": {
        "west": 225,
        "east": 223,
        "north": 121
      },
      "id": 224
    },
    {
      "name": "Brimstone",
      "exits": {
        "east": 224,
        "north": 122
      },
      "id": 225
    },
    {
      "name": "A peaceful park",
      "exits": {
        "south": 117,
        "west": 227,
        "east": 172,
        "north": 232
      },
      "id": 226
    },
    {
      "name": "A peaceful park",
      "exits": {
        "south": 118,
        "west": 230,
        "east": 226,
        "north": 228
      },
      "id": 227
    },
    {
      "name": "A peaceful park",
      "exits": {
        "south": 227,
        "west": 231,
        "east": 232,
        "north": 229
      },
      "id": 228
    },
    {
      "name": "Sanctuary",
      "exits": {
        "up": 893,
        "south": 228
      },
      "id": 229
    },
    {
      "name": "A peaceful park",
      "exits": {
        "south": 119,
        "west": 815,
        "east": 227,
        "north": 231
      },
      "id": 230
    },
    {
      "name": "A peaceful park",
      "exits": {
        "south": 230,
        "west": 796,
        "east": 228,
        "north": 426
      },
      "id": 231
    },
    {
      "name": "A peaceful park",
      "exits": {
        "south": 226,
        "west": 228,
        "east": 173,
        "north": 234
      },
      "id": 232
    },
    {
      "name": "The Shadowed Anvil",
      "exits": {
        "west": 220,
        "north": 116
      },
      "id": 233
    },
    {
      "name": "Andre's Clothing",
      "exits": {
        "south": 232
      },
      "id": 234
    },
    {
      "name": "Smoke House",
      "exits": {
        "south": 210
      },
      "id": 394
    },
    {
      "name": "The Lathe",
      "exits": {
        "south": 209
      },
      "id": 395
    },
    {
      "name": "Antique Shop",
      "exits": {
        "south": 208
      },
      "id": 396
    },
    {
      "name": "Mage's House",
      "exits": {
        "east": 398,
        "south": 206
      },
      "id": 397
    },
    {
      "name": "Mage's Apprentice House",
      "exits": {
        "west": 397
      },
      "id": 398
    },
    {
      "name": "Retired Warrior's House",
      "exits": {
        "up": 734,
        "west": 213
      },
      "id": 399
    },
    {
      "name": "Bell maker's shop",
      "exits": {
        "east": 214
      },
      "id": 400
    },
    {
      "name": "Candle Shop",
      "exits": {
        "west": 214
      },
      "id": 401
    },
    {
      "name": "Do-it-Yourself Distiller",
      "exits": {
        "east": 216
      },
      "id": 402
    },
    {
      "name": "Entrance to a temple",
      "exits": {
        "east": 404,
        "west": 216
      },
      "id": 403
    },
    {
      "name": "Temple of Amaterasu",
      "exits": {
        "east": 405,
        "west": 403
      },
      "id": 404
    },
    {
      "name": "Temple of Amaterasu",
      "exits": {
        "west": 404,
        "south": 407,
        "north": 406
      },
      "id": 405
    },
    {
      "name": "Candle Room",
      "exits": {
        "south": 405
      },
      "id": 406
    },
    {
      "name": "Quiet Room",
      "exits": {
        "north": 405
      },
      "id": 407
    },
    {
      "name": "MD Banking",
      "exits": {
        "east": 217
      },
      "id": 408
    },
    {
      "name": "Bounty Room",
      "exits": {
        "east": 219
      },
      "id": 409
    },
    {
      "name": "A dingy alleyway",
      "exits": {
        "west": 411,
        "south": 122,
        "north": 792
      },
      "id": 410
    },
    {
      "name": "Vesla Times Press Office",
      "exits": {
        "east": 410,
        "south": 123
      },
      "id": 411
    },
    {
      "name": "Smithy",
      "exits": {
        "west": 160,
        "south": 124
      },
      "id": 412
    },
    {
      "name": "A dark alleyway",
      "exits": {
        "north": 129
      },
      "id": 419
    },
    {
      "name": "The Old Temple",
      "exits": {
        "north": 130
      },
      "id": 420
    },
    {
      "name": "Mage's Guild",
      "exits": {
        "north": 132
      },
      "id": 421
    },
    {
      "name": "Mercantile Guild Office",
      "exits": {
        "east": 837,
        "west": 155
      },
      "id": 422
    },
    {
      "name": "Glassblower",
      "exits": {
        "east": 155
      },
      "id": 423
    },
    {
      "name": "Fighter's Guild",
      "exits": {
        "west": 156
      },
      "id": 424
    },
    {
      "name": "Omar's Oils II",
      "exits": {
        "south": 121
      },
      "id": 425
    },
    {
      "name": "Deora's Outfitters",
      "exits": {
        "south": 231
      },
      "id": 426
    },
    {
      "name": "Weapon Master's Bedroom",
      "exits": {
        "down": 399
      },
      "id": 734
    },
    {
      "name": "Guild/Shop Space for rent",
      "exits": {
        "west": 172
      },
      "id": 735
    },
    {
      "name": "Guild/Shop Space for rent",
      "exits": {
        "west": 173
      },
      "id": 736
    },
    {
      "name": "Chamber of Commerce",
      "exits": {
        "south": 187
      },
      "id": 737
    },
    {
      "name": "Alley",
      "exits": {
        "south": 188
      },
      "id": 738
    },
    {
      "name": "The School of Guild Skills",
      "exits": {
        "north": 189
      },
      "id": 739
    },
    {
      "name": "Stationery Store",
      "exits": {
        "north": 190
      },
      "id": 740
    },
    {
      "name": "Dormitory Hallway",
      "exits": {
        "up": 748,
        "south": 190,
        "east": 747,
        "north": 745
      },
      "id": 741
    },
    {
      "name": "Magoo's Bookstore",
      "exits": {
        "north": 191
      },
      "id": 742
    },
    {
      "name": "Frenchie's Cafe",
      "exits": {
        "south": 191
      },
      "id": 743
    },
    {
      "name": "An empty lot.",
      "exits": {
        "north": 192
      },
      "id": 744
    },
    {
      "name": "Dormitory Kitchen",
      "exits": {
        "east": 746,
        "south": 741
      },
      "id": 745
    },
    {
      "name": "Store Room",
      "exits": {
        "west": 745
      },
      "id": 746
    },
    {
      "name": "Dormitory Administrator's Room",
      "exits": {
        "west": 741
      },
      "id": 747
    },
    {
      "name": "Dormitory Hallway",
      "exits": {
        "west": 751,
        "down": 741,
        "south": 752,
        "east": 750,
        "north": 749
      },
      "id": 748
    },
    {
      "name": "Dormer",
      "exits": {
        "south": 748
      },
      "id": 749
    },
    {
      "name": "Dormer",
      "exits": {
        "west": 748
      },
      "id": 750
    },
    {
      "name": "Dormer",
      "exits": {
        "east": 748
      },
      "id": 751
    },
    {
      "name": "Dormer",
      "exits": {
        "north": 748
      },
      "id": 752
    },
    {
      "name": "The drawbridge",
      "exits": {
        "southwest": 169,
        "north": 754
      },
      "id": 753
    },
    {
      "name": "Between the towers",
      "exits": {
        "south": 753,
        "north": 755
      },
      "id": 754
    },
    {
      "name": "Between the towers",
      "exits": {
        "south": 754,
        "north": 756
      },
      "id": 755
    },
    {
      "name": "The inner ward",
      "exits": {
        "south": 755,
        "north": 757
      },
      "id": 756
    },
    {
      "name": "The inner ward",
      "exits": {
        "south": 756,
        "northeast": 765,
        "east": 758,
        "north": 766
      },
      "id": 757
    },
    {
      "name": "The inner ward",
      "exits": {
        "west": 757,
        "south": 759,
        "northwest": 766,
        "north": 765
      },
      "id": 758
    },
    {
      "name": "Eastern guard room",
      "exits": {
        "northeast": 760,
        "north": 758
      },
      "id": 759
    },
    {
      "name": "Lower eastern stairwell",
      "exits": {
        "southwest": 759,
        "up": 761
      },
      "id": 760
    },
    {
      "name": "Middle eastern stairwell",
      "exits": {
        "southwest": 762,
        "down": 760,
        "up": 763
      },
      "id": 761
    },
    {
      "name": "Eastern guard quarters",
      "exits": {
        "northeast": 761
      },
      "id": 762
    },
    {
      "name": "Upper eastern stairwell",
      "exits": {
        "southwest": 764,
        "down": 761
      },
      "id": 763
    },
    {
      "name": "Eastern tower observatory",
      "exits": {
        "northeast": 763
      },
      "id": 764
    },
    {
      "name": "The inner ward",
      "exits": {
        "west": 766,
        "northwest": 767,
        "south": 758,
        "southwest": 757,
        "northeast": 769,
        "east": 770,
        "north": 768
      },
      "id": 765
    },
    {
      "name": "The inner ward",
      "exits": {
        "southeast": 758,
        "south": 757,
        "northeast": 768,
        "east": 765,
        "north": 767
      },
      "id": 766
    },
    {
      "name": "The inner ward",
      "exits": {
        "east": 768,
        "southeast": 765,
        "south": 766
      },
      "id": 767
    },
    {
      "name": "The inner ward",
      "exits": {
        "southwest": 766,
        "west": 767,
        "east": 769,
        "south": 765
      },
      "id": 768
    },
    {
      "name": "The well",
      "exits": {
        "southwest": 765,
        "east": 771,
        "west": 768
      },
      "id": 769
    },
    {
      "name": "Castle stables",
      "exits": {
        "south": 790,
        "west": 765,
        "east": 773,
        "north": 791
      },
      "id": 770
    },
    {
      "name": "The blacksmith",
      "exits": {
        "east": 772,
        "west": 769
      },
      "id": 771
    },
    {
      "name": "The storage room",
      "exits": {
        "west": 771
      },
      "id": 772
    },
    {
      "name": "Castle stables",
      "exits": {
        "south": 789,
        "west": 770,
        "east": 774,
        "north": 788
      },
      "id": 773
    },
    {
      "name": "Castle stables",
      "exits": {
        "south": 787,
        "west": 773,
        "east": 775,
        "north": 786
      },
      "id": 774
    },
    {
      "name": "Castle stables",
      "exits": {
        "south": 784,
        "west": 774,
        "east": 776,
        "north": 785
      },
      "id": 775
    },
    {
      "name": "Castle stables",
      "exits": {
        "south": 782,
        "west": 775,
        "east": 777,
        "north": 781
      },
      "id": 776
    },
    {
      "name": "Small paddock",
      "exits": {
        "southeast": 779,
        "south": 783,
        "west": 776,
        "east": 778,
        "north": 780
      },
      "id": 777
    },
    {
      "name": "Small paddock",
      "exits": {
        "southwest": 783,
        "west": 777,
        "northwest": 780,
        "south": 779
      },
      "id": 778
    },
    {
      "name": "Small paddock",
      "exits": {
        "west": 783,
        "northwest": 777,
        "north": 778
      },
      "id": 779
    },
    {
      "name": "Wash area",
      "exits": {
        "southeast": 778,
        "south": 777
      },
      "id": 780
    },
    {
      "name": "You swing open the wooden door and enter the stall.",
      "exits": {
        "south": 776
      },
      "id": 781
    },
    {
      "name": "You swing open the wooden door and enter the stall.",
      "exits": {
        "north": 776
      },
      "id": 782
    },
    {
      "name": "Small paddock",
      "exits": {
        "northeast": 778,
        "east": 779,
        "north": 777
      },
      "id": 783
    },
    {
      "name": "You swing open the wooden door and enter the stall.",
      "exits": {
        "north": 775
      },
      "id": 784
    },
    {
      "name": "You swing open the wooden door and enter the stall.",
      "exits": {
        "south": 775
      },
      "id": 785
    },
    {
      "name": "Tack room",
      "exits": {
        "south": 774
      },
      "id": 786
    },
    {
      "name": "Feed room",
      "exits": {
        "north": 774
      },
      "id": 787
    },
    {
      "name": "You swing open the wooden door and enter the stall.",
      "exits": {
        "south": 773
      },
      "id": 788
    },
    {
      "name": "You swing open the wooden door and enter the stall.",
      "exits": {
        "north": 773
      },
      "id": 789
    },
    {
      "name": "You swing open the wooden door and enter the stall.",
      "exits": {
        "north": 770
      },
      "id": 790
    },
    {
      "name": "You swing open the wooden door and enter the stall.",
      "exits": {
        "south": 770
      },
      "id": 791
    },
    {
      "name": "A dingy alleyway",
      "exits": {
        "south": 410,
        "east": 795,
        "north": 794
      },
      "id": 792
    },
    {
      "name": "Effortlessly, you scale the brick wall and drop into a garden on the opposite",
      "exits": {
        "east": 168
      },
      "id": 793
    },
    {
      "name": "A small building.",
      "exits": {
        "south": 792
      },
      "id": 794
    },
    {
      "name": "A dingy alleyway",
      "exits": {
        "south": 813,
        "west": 792,
        "east": 796,
        "north": 797
      },
      "id": 795
    },
    {
      "name": "An alley",
      "exits": {
        "south": 814,
        "west": 795,
        "east": 231,
        "north": 961
      },
      "id": 796
    },
    {
      "name": "A dingy alley",
      "exits": {
        "south": 795,
        "north": 798
      },
      "id": 797
    },
    {
      "name": "A Dingy Alley",
      "exits": {
        "south": 797,
        "north": 799
      },
      "id": 798
    },
    {
      "name": "Stink Alley Way",
      "exits": {
        "west": 802,
        "east": 800,
        "south": 798
      },
      "id": 799
    },
    {
      "name": "Stink Alley Way",
      "exits": {
        "west": 799,
        "east": 801,
        "north": 806
      },
      "id": 800
    },
    {
      "name": "Stink Alley Way",
      "exits": {
        "west": 800
      },
      "id": 801
    },
    {
      "name": "Stink Alley Way",
      "exits": {
        "south": 805,
        "west": 803,
        "east": 799,
        "north": 807
      },
      "id": 802
    },
    {
      "name": "Stink Alley Way",
      "exits": {
        "east": 802,
        "south": 804
      },
      "id": 803
    },
    {
      "name": "Fish Mongery",
      "exits": {
        "north": 803
      },
      "id": 804
    },
    {
      "name": "Crazy Habib's Fertilizer",
      "exits": {
        "north": 802
      },
      "id": 805
    },
    {
      "name": "Barber Shop",
      "exits": {
        "south": 800
      },
      "id": 806
    },
    {
      "name": "Pornographers Den",
      "exits": {
        "south": 802
      },
      "id": 807
    },
    {
      "name": "Livery",
      "exits": {
        "up": 809,
        "west": 161
      },
      "id": 808
    },
    {
      "name": "Hayloft",
      "exits": {
        "down": 808
      },
      "id": 809
    },
    {
      "name": "Tailor's Shop",
      "exits": {
        "west": 162
      },
      "id": 810
    },
    {
      "name": "Hardware Store",
      "exits": {
        "west": 163
      },
      "id": 811
    },
    {
      "name": "Haseltine Engravers",
      "exits": {
        "west": 164
      },
      "id": 812
    },
    {
      "name": "Guild/Shop Space for rent",
      "exits": {
        "north": 795
      },
      "id": 813
    },
    {
      "name": "Flea Market",
      "exits": {
        "north": 796
      },
      "id": 814
    },
    {
      "name": "The Back Room",
      "exits": {
        "east": 230,
        "north": 814
      },
      "id": 815
    },
    {
      "name": "Castle Bridge",
      "exits": {
        "north": 151
      },
      "id": 816
    },
    {
      "name": "Manor House",
      "exits": {
        "up": 818,
        "west": 152
      },
      "id": 817
    },
    {
      "name": "Manor House",
      "exits": {
        "down": 817
      },
      "id": 818
    },
    {
      "name": "Guild/Shop Space for rent",
      "exits": {
        "east": 152
      },
      "id": 819
    },
    {
      "name": "Cleric Guild",
      "exits": {
        "west": 839,
        "east": 153,
        "north": 838
      },
      "id": 820
    },
    {
      "name": "Hall of the builders guild",
      "exits": {
        "west": 154
      },
      "id": 821
    },
    {
      "name": "City Hall",
      "exits": {
        "east": 156,
        "up": 831
      },
      "id": 822
    },
    {
      "name": "Tea Shop",
      "exits": {
        "east": 157
      },
      "id": 823
    },
    {
      "name": "Whore House",
      "exits": {
        "east": 158,
        "up": 825
      },
      "id": 824
    },
    {
      "name": "Second floor of whore house.",
      "exits": {
        "south": 828,
        "west": 826,
        "up": 829,
        "down": 824,
        "north": 827
      },
      "id": 825
    },
    {
      "name": "Viking's room",
      "exits": {
        "east": 825
      },
      "id": 826
    },
    {
      "name": "Sandra's room",
      "exits": {
        "south": 825
      },
      "id": 827
    },
    {
      "name": "Kathy's room",
      "exits": {
        "north": 825
      },
      "id": 828
    },
    {
      "name": "Robert's room",
      "exits": {
        "down": 825
      },
      "id": 829
    },
    {
      "name": "Baker's Shop",
      "exits": {
        "west": 157
      },
      "id": 830
    },
    {
      "name": "First Floor",
      "exits": {
        "up": 833,
        "down": 822,
        "west": 832
      },
      "id": 831
    },
    {
      "name": "Chamber of Commerce",
      "exits": {
        "east": 831
      },
      "id": 832
    },
    {
      "name": "Second Floor",
      "exits": {
        "up": 835,
        "down": 831,
        "west": 834
      },
      "id": 833
    },
    {
      "name": "Magistrate",
      "exits": {
        "east": 833
      },
      "id": 834
    },
    {
      "name": "City Archives",
      "exits": {
        "down": 833,
        "west": 836
      },
      "id": 835
    },
    {
      "name": "Inner Sanctum",
      "exits": {
        "east": 835
      },
      "id": 836
    },
    {
      "name": "Open Air Market:",
      "exits": {
        "west": 422
      },
      "id": 837
    },
    {
      "name": "Chapel of War",
      "exits": {
        "south": 820
      },
      "id": 838
    },
    {
      "name": "Reconciliation Chapel",
      "exits": {
        "east": 820
      },
      "id": 839
    },
    {
      "name": "Burned Area",
      "exits": {
        "west": 841,
        "south": 148
      },
      "id": 840
    },
    {
      "name": "Burned Area",
      "exits": {
        "south": 147,
        "west": 842,
        "east": 840,
        "north": 843
      },
      "id": 841
    },
    {
      "name": "Burned Area",
      "exits": {
        "south": 146,
        "east": 841,
        "north": 844
      },
      "id": 842
    },
    {
      "name": "Burned Area",
      "exits": {
        "west": 844,
        "south": 841,
        "north": 201
      },
      "id": 843
    },
    {
      "name": "Burned Area",
      "exits": {
        "south": 842,
        "east": 843,
        "north": 202
      },
      "id": 844
    },
    {
      "name": "Burned Area",
      "exits": {
        "east": 846,
        "north": 146
      },
      "id": 845
    },
    {
      "name": "Burned Area",
      "exits": {
        "west": 845,
        "north": 147
      },
      "id": 846
    },
    {
      "name": "Old City Offices",
      "exits": {
        "west": 849,
        "east": 848,
        "north": 144
      },
      "id": 847
    },
    {
      "name": "Old Office",
      "exits": {
        "west": 847
      },
      "id": 848
    },
    {
      "name": "Old Office",
      "exits": {
        "east": 847
      },
      "id": 849
    },
    {
      "name": "Howling Wolf Inn",
      "exits": {
        "west": 142,
        "east": 852,
        "north": 851
      },
      "id": 850
    },
    {
      "name": "Howling Wolf Inn",
      "exits": {
        "south": 850
      },
      "id": 851
    },
    {
      "name": "Howling Wolf Inn",
      "exits": {
        "west": 850
      },
      "id": 852
    },
    {
      "name": "Abandoned Building",
      "exits": {
        "east": 139
      },
      "id": 853
    },
    {
      "name": "Spice Merchant",
      "exits": {
        "west": 139
      },
      "id": 854
    },
    {
      "name": "Abandoned Building",
      "exits": {
        "west": 138
      },
      "id": 855
    },
    {
      "name": "Carvings Shop",
      "exits": {
        "east": 138
      },
      "id": 856
    },
    {
      "name": "Abandoned Warehouse",
      "exits": {
        "west": 198
      },
      "id": 857
    },
    {
      "name": "In Rohan's bedroom",
      "exits": {
        "down": 869,
        "up": 871
      },
      "id": 870
    },
    {
      "name": "In Gwyneth's bedroom",
      "exits": {
        "down": 873,
        "up": 872
      },
      "id": 871
    },
    {
      "name": "In Vella's bedroom",
      "exits": {
        "down": 871
      },
      "id": 872
    },
    {
      "name": "<> Aladrin escapes reality and falls into Moral Decay. <>",
      "exits": {
        "down": 874,
        "up": 871
      },
      "id": 873
    },
    {
      "name": "Bottom floor of the silo",
      "exits": {
        "up": 873
      },
      "id": 874
    },
    {
      "name": "Guild/Shop Space for rent",
      "exits": {
        "south": 127
      },
      "id": 878
    },
    {
      "name": "Vesla Post Office",
      "exits": {
        "south": 126
      },
      "id": 879
    },
    {
      "name": "Old Adventurer's Guild",
      "exits": {
        "north": 126
      },
      "id": 880
    },
    {
      "name": "The Players' lounge",
      "exits": {
        "down": 229
      },
      "id": 893
    },
    {
      "name": "Rising Phoenix",
      "exits": {
        "south": 796
      },
      "id": 961
    },
    {
      "name": "Abandoned Store",
      "exits": {
        "west": 199
      },
      "id": 962
    }
  ],
  "exportedAt": "2026-01-05T00:19:21Z"
}
